Metadata-Version: 2.4
Name: graphsense-bitcoin-etl
Version: 1.5.5
Summary: Tools for exporting Bitcoin blockchain data to JSON
Home-page: https://github.com/blockchain-etl/bitcoin-etl
Author: Iknaio Cryptoasset Analytics GmbH
Author-email: contact@ikna.io
Project-URL: Bug Reports, https://github.com/blockchain-etl/bitcoin-etl/issues
Project-URL: Chat, https://gitter.im/ethereum-etl/Lobby
Project-URL: Source, https://github.com/blockchain-etl/bitcoin-etl
Keywords: bitcoin
Classifier: Development Status :: 5 - Production/Stable
Classifier: Intended Audience :: Developers
Classifier: License :: OSI Approved :: MIT License
Classifier: Programming Language :: Python :: 3
Classifier: Programming Language :: Python :: 3.5
Classifier: Programming Language :: Python :: 3.6
Classifier: Programming Language :: Python :: 3.7
Requires-Python: >=3.5.0,<4
License-File: LICENSE
Requires-Dist: requests~=2.20
Requires-Dist: python-dateutil~=2.7
Requires-Dist: click>=7.0
Provides-Extra: streaming
Requires-Dist: timeout-decorator==0.4.1; extra == "streaming"
Requires-Dist: google-cloud-pubsub==0.39.1; extra == "streaming"
Provides-Extra: dev
Requires-Dist: pytest~=4.3.0; extra == "dev"
Dynamic: author
Dynamic: author-email
Dynamic: classifier
Dynamic: description
Dynamic: description-content-type
Dynamic: home-page
Dynamic: keywords
Dynamic: license-file
Dynamic: project-url
Dynamic: provides-extra
Dynamic: requires-dist
Dynamic: requires-python
Dynamic: summary
